Metadata-Version: 1.0
Name: Bino-gau
Version: 0.1
Summary: Gaussian and Binomial distributions
Home-page: UNKNOWN
Author: Mudit Painuli
Author-email: muditpainuli@gmail.com
License: UNKNOWN
Platform: UNKNOWN
